{
	"midi" : [
		"name",
		"group",
		"beat",
		"time",
		"amp",
		"note",
		"env",
		"out",
		"clock",
		"poly"
	],

	"emitter" : [
		"name",
		"address",
		"group",
		"time",
		"beat"
	],

	"osc" : [
		"name",
		"address",
		"group",
		"time",
		"beat"
	],

	"synth" : [
		"amp",
		"beat",
		"env",
		"note",
		"time",
		"pan",
		"slide",
		"sub",
		"add_fx",
		"res",
		"wave2",
		"group",
		"name",
		"out",
		"fm_env",
		"fm_harm",
		"fm_idx"
	],

	"noise" : [
		"amp",
		"beat",
		"env",
		"time",
		"pan",
		"add_fx",
		"group",
		"name",
		"out"
	],

	"polySynth" : [
		"amp",
		"beat",
		"env",
		"note",
		"time",
		"pan",
		"slide",
		"sub",
		"add_fx",
		"res",
		"wave2",
		"group",
		"name",
		"out"
	],

	"sample" : [
		"amp",
		"beat",
		"env",
		"time",
		"pan",
		"speed",
		"add_fx",
		"stretch",
		"group",
		"name",
		"out",
		"offset"
	],
	
	"loop" : [
		"amp",
		"beat",
		"env",
		"time",
		"pan",
		"speed",
		"add_fx",
		"stretch",
		"group",
		"name",
		"out",
		"offset"
	],

	"polySample" : [
		"amp",
		"beat",
		"env",
		"time",
		"pan",
		"speed",
		"add_fx",
		"stretch",
		"group",
		"name",
		"out",
		"offset"
	],

	"input" : [
		"time",
		"beat",
		"amp",
		"env",
		"pan",
		"group",
		"name",
		"out",
		"add_fx"
	]
}